README.md
setup.py
stringsan/__init__.py
stringsan.egg-info/PKG-INFO
stringsan.egg-info/SOURCES.txt
stringsan.egg-info/dependency_links.txt
stringsan.egg-info/top_level.txt
stringsan/email/__init__.py
stringsan/strings/__init__.py
tests/__init__.py
tests/test_email.py
tests/test_strings.py