Metadata-Version: 2.1
Name: stringsan
Version: 0.2
Summary: String manipulation package that makes your life easier
Home-page: https://github.com/ArrancarDev/stringsan
Author: ArrancarDev
Author-email: arrancar.dev@outlook.com
Classifier: Programming Language :: Python :: 3
Classifier: License :: OSI Approved :: MIT License
Classifier: Operating System :: OS Independent
Requires-Python: >=3.6
